rpgpy/data.pypy311-pp73-darwin.so
rpgpy/metadata.py
rpgpy/version.py
rpgpy/header.py
rpgpy/spcutil.py
rpgpy/__init__.py
rpgpy/data.pyx
rpgpy/utils.py
rpgpy/py.typed
rpgpy/data.c
rpgpy/nc.py
rpgpy-0.15.13.dist-info/RECORD
rpgpy-0.15.13.dist-info/WHEEL
rpgpy-0.15.13.dist-info/top_level.txt
rpgpy-0.15.13.dist-info/METADATA
rpgpy-0.15.13.dist-info/licenses/LICENSE
