Metadata-Version: 2.4
Name: rpgPy
Version: 0.15.13
Summary: Cython code for reading binary files from RPG cloud radar.
Author-email: Simo Tukiainen <simo.tukiainen@fmi.fi>
License: MIT License
Project-URL: Homepage, https://github.com/actris-cloudnet/rpgpy
Project-URL: Repository, https://github.com/actris-cloudnet/rpgpy
Project-URL: Changelog, https://github.com/actris-cloudnet/rpgpy/blob/main/CHANGELOG.md
Classifier: Development Status :: 4 - Beta
Classifier: Intended Audience :: Science/Research
Classifier: License :: OSI Approved :: MIT License
Classifier: Programming Language :: Python :: 3.10
Classifier: Programming Language :: Python :: 3.11
Classifier: Programming Language :: Python :: 3.12
Classifier: Programming Language :: Python :: 3.13
Classifier: Topic :: Scientific/Engineering
Requires-Python: >=3.10
License-File: LICENSE
Requires-Dist: cython
Requires-Dist: netCDF4
Requires-Dist: numpy
Requires-Dist: tqdm
Provides-Extra: full
Requires-Dist: numba; extra == "full"
Provides-Extra: test
Requires-Dist: mypy; extra == "test"
Requires-Dist: pytest-flakefinder; extra == "test"
Requires-Dist: types-tqdm; extra == "test"
Provides-Extra: dev
Requires-Dist: pre-commit; extra == "dev"
Requires-Dist: release-version; extra == "dev"
Dynamic: license-file
